octoflow/__init__.py
octoflow/config.py
octoflow/constants.py
octoflow/exceptions.py
octoflow/logging.py
octoflow/plugin.py
octoflow/typing.py
octoflow/core/__init__.py
octoflow/core/meta.py
octoflow/data/__init__.py
octoflow/data/base.py
octoflow/data/dataclass.py
octoflow/data/dataset.py
octoflow/data/expression.py
octoflow/data/loaders.py
octoflow/data/metadata.py
octoflow/data/sampler.py
octoflow/data/schema.py
octoflow/data/types.py
octoflow/pipeline/__init__.py
octoflow/pipeline/pipeline.py
octoflow/pipeline/task.py
octoflow/tracking/__init__.py
octoflow/tracking/experiment.py
octoflow/tracking/run.py
octoflow/tracking/artifact/__init__.py
octoflow/tracking/artifact/handler.py
octoflow/utils/__init__.py
octoflow/utils/cache.py
octoflow/utils/collections.py
octoflow/utils/config.py
octoflow/utils/func.py
octoflow/utils/hashing.py
octoflow/utils/html.py
octoflow/utils/notebbok.py
octoflow/utils/objects.py
octoflow/utils/progbar.py
octoflow/utils/rsync.py
octoflow/utils/sqlitedict.py
octoflow/utils/string.py
octoflow/utils/validate.py
octoflow-0.2.0.dist-info/METADATA
octoflow-0.2.0.dist-info/WHEEL
octoflow-0.2.0.dist-info/licenses/AUTHORS.md
octoflow-0.2.0.dist-info/licenses/LICENSE
octoflow-0.2.0.dist-info/RECORD
