Metadata-Version: 2.1
Name: octoflow
Version: 0.2.0
Summary: Streamlining machine learning tracking for seamless experiment management.
Project-URL: Documentation, https://github.com/ysenarath/octoflow
Project-URL: Source, https://github.com/ysenarath/octoflow
Author-email: Yasas Senarath <email@example.com>
License-Expression: MIT
License-File: AUTHORS.md
License-File: LICENSE
Keywords: machine-learning,tracking
Classifier: Development Status :: 2 - Pre-Alpha
Classifier: Programming Language :: Python
Classifier: Programming Language :: Python :: 3.10
Classifier: Programming Language :: Python :: 3.11
Classifier: Programming Language :: Python :: Implementation :: CPython
Requires-Python: >=3.8
Requires-Dist: cloudpickle
Requires-Dist: dill
Requires-Dist: filelock>=3.13.4
Requires-Dist: octoflow-plugins
Requires-Dist: omegaconf>=2.3.0
Requires-Dist: pandas>=2.2.2
Requires-Dist: polars>=0.20.22
Requires-Dist: pyarrow>=16.0.0
Requires-Dist: sqlalchemy
Requires-Dist: tabulate>=0.9.0
Requires-Dist: tqdm>=4.66.2
Requires-Dist: xxhash
